enermap/__init__.py
enermap/common.py
enermap/enermap.py
enermap-0.0.2.dist-info/LICENSE
enermap-0.0.2.dist-info/METADATA
enermap-0.0.2.dist-info/WHEEL
enermap-0.0.2.dist-info/top_level.txt
enermap-0.0.2.dist-info/RECORD
